{"d:\\OneDrive\\桌面\\stm32\\9-1 串口发送\\Hardware\\Buzzer.c":"d:\\OneDrive\\桌面\\stm32\\9-1 串口发送\\build\\Target 1\\.obj\\Hardware\\Buzzer.o","d:\\OneDrive\\桌面\\stm32\\9-1 串口发送\\Hardware\\CountSensor.c":"d:\\OneDrive\\桌面\\stm32\\9-1 串口发送\\build\\Target 1\\.obj\\Hardware\\CountSensor.o","d:\\OneDrive\\桌面\\stm32\\9-1 串口发送\\Hardware\\Key.c":"d:\\OneDrive\\桌面\\stm32\\9-1 串口发送\\build\\Target 1\\.obj\\Hardware\\Key.o","d:\\OneDrive\\桌面\\stm32\\9-1 串口发送\\Hardware\\LED.c":"d:\\OneDrive\\桌面\\stm32\\9-1 串口发送\\build\\Target 1\\.obj\\Hardware\\LED.o","d:\\OneDrive\\桌面\\stm32\\9-1 串口发送\\Hardware\\LightSensor.c":"d:\\OneDrive\\桌面\\stm32\\9-1 串口发送\\build\\Target 1\\.obj\\Hardware\\LightSensor.o","d:\\OneDrive\\桌面\\stm32\\9-1 串口发送\\Hardware\\Serial.c":"d:\\OneDrive\\桌面\\stm32\\9-1 串口发送\\build\\Target 1\\.obj\\Hardware\\Serial.o","d:\\OneDrive\\桌面\\stm32\\9-1 串口发送\\Library\\misc.c":"d:\\OneDrive\\桌面\\stm32\\9-1 串口发送\\build\\Target 1\\.obj\\Library\\misc.o","d:\\OneDrive\\桌面\\stm32\\9-1 串口发送\\Library\\stm32f10x_adc.c":"d:\\OneDrive\\桌面\\stm32\\9-1 串口发送\\build\\Target 1\\.obj\\Library\\stm32f10x_adc.o","d:\\OneDrive\\桌面\\stm32\\9-1 串口发送\\Library\\stm32f10x_bkp.c":"d:\\OneDrive\\桌面\\stm32\\9-1 串口发送\\build\\Target 1\\.obj\\Library\\stm32f10x_bkp.o","d:\\OneDrive\\桌面\\stm32\\9-1 串口发送\\Library\\stm32f10x_can.c":"d:\\OneDrive\\桌面\\stm32\\9-1 串口发送\\build\\Target 1\\.obj\\Library\\stm32f10x_can.o","d:\\OneDrive\\桌面\\stm32\\9-1 串口发送\\Library\\stm32f10x_cec.c":"d:\\OneDrive\\桌面\\stm32\\9-1 串口发送\\build\\Target 1\\.obj\\Library\\stm32f10x_cec.o","d:\\OneDrive\\桌面\\stm32\\9-1 串口发送\\Library\\stm32f10x_crc.c":"d:\\OneDrive\\桌面\\stm32\\9-1 串口发送\\build\\Target 1\\.obj\\Library\\stm32f10x_crc.o","d:\\OneDrive\\桌面\\stm32\\9-1 串口发送\\Library\\stm32f10x_dac.c":"d:\\OneDrive\\桌面\\stm32\\9-1 串口发送\\build\\Target 1\\.obj\\Library\\stm32f10x_dac.o","d:\\OneDrive\\桌面\\stm32\\9-1 串口发送\\Library\\stm32f10x_dbgmcu.c":"d:\\OneDrive\\桌面\\stm32\\9-1 串口发送\\build\\Target 1\\.obj\\Library\\stm32f10x_dbgmcu.o","d:\\OneDrive\\桌面\\stm32\\9-1 串口发送\\Library\\stm32f10x_dma.c":"d:\\OneDrive\\桌面\\stm32\\9-1 串口发送\\build\\Target 1\\.obj\\Library\\stm32f10x_dma.o","d:\\OneDrive\\桌面\\stm32\\9-1 串口发送\\Library\\stm32f10x_exti.c":"d:\\OneDrive\\桌面\\stm32\\9-1 串口发送\\build\\Target 1\\.obj\\Library\\stm32f10x_exti.o","d:\\OneDrive\\桌面\\stm32\\9-1 串口发送\\Library\\stm32f10x_flash.c":"d:\\OneDrive\\桌面\\stm32\\9-1 串口发送\\build\\Target 1\\.obj\\Library\\stm32f10x_flash.o","d:\\OneDrive\\桌面\\stm32\\9-1 串口发送\\Library\\stm32f10x_fsmc.c":"d:\\OneDrive\\桌面\\stm32\\9-1 串口发送\\build\\Target 1\\.obj\\Library\\stm32f10x_fsmc.o","d:\\OneDrive\\桌面\\stm32\\9-1 串口发送\\Library\\stm32f10x_gpio.c":"d:\\OneDrive\\桌面\\stm32\\9-1 串口发送\\build\\Target 1\\.obj\\Library\\stm32f10x_gpio.o","d:\\OneDrive\\桌面\\stm32\\9-1 串口发送\\Library\\stm32f10x_i2c.c":"d:\\OneDrive\\桌面\\stm32\\9-1 串口发送\\build\\Target 1\\.obj\\Library\\stm32f10x_i2c.o","d:\\OneDrive\\桌面\\stm32\\9-1 串口发送\\Library\\stm32f10x_iwdg.c":"d:\\OneDrive\\桌面\\stm32\\9-1 串口发送\\build\\Target 1\\.obj\\Library\\stm32f10x_iwdg.o","d:\\OneDrive\\桌面\\stm32\\9-1 串口发送\\Library\\stm32f10x_pwr.c":"d:\\OneDrive\\桌面\\stm32\\9-1 串口发送\\build\\Target 1\\.obj\\Library\\stm32f10x_pwr.o","d:\\OneDrive\\桌面\\stm32\\9-1 串口发送\\Library\\stm32f10x_rcc.c":"d:\\OneDrive\\桌面\\stm32\\9-1 串口发送\\build\\Target 1\\.obj\\Library\\stm32f10x_rcc.o","d:\\OneDrive\\桌面\\stm32\\9-1 串口发送\\Library\\stm32f10x_rtc.c":"d:\\OneDrive\\桌面\\stm32\\9-1 串口发送\\build\\Target 1\\.obj\\Library\\stm32f10x_rtc.o","d:\\OneDrive\\桌面\\stm32\\9-1 串口发送\\Library\\stm32f10x_sdio.c":"d:\\OneDrive\\桌面\\stm32\\9-1 串口发送\\build\\Target 1\\.obj\\Library\\stm32f10x_sdio.o","d:\\OneDrive\\桌面\\stm32\\9-1 串口发送\\Library\\stm32f10x_spi.c":"d:\\OneDrive\\桌面\\stm32\\9-1 串口发送\\build\\Target 1\\.obj\\Library\\stm32f10x_spi.o","d:\\OneDrive\\桌面\\stm32\\9-1 串口发送\\Library\\stm32f10x_tim.c":"d:\\OneDrive\\桌面\\stm32\\9-1 串口发送\\build\\Target 1\\.obj\\Library\\stm32f10x_tim.o","d:\\OneDrive\\桌面\\stm32\\9-1 串口发送\\Library\\stm32f10x_usart.c":"d:\\OneDrive\\桌面\\stm32\\9-1 串口发送\\build\\Target 1\\.obj\\Library\\stm32f10x_usart.o","d:\\OneDrive\\桌面\\stm32\\9-1 串口发送\\Library\\stm32f10x_wwdg.c":"d:\\OneDrive\\桌面\\stm32\\9-1 串口发送\\build\\Target 1\\.obj\\Library\\stm32f10x_wwdg.o","d:\\OneDrive\\桌面\\stm32\\9-1 串口发送\\Start\\core_cm3.c":"d:\\OneDrive\\桌面\\stm32\\9-1 串口发送\\build\\Target 1\\.obj\\Start\\core_cm3.o","d:\\OneDrive\\桌面\\stm32\\9-1 串口发送\\Start\\startup_stm32f10x_md.s":"d:\\OneDrive\\桌面\\stm32\\9-1 串口发送\\build\\Target 1\\.obj\\Start\\startup_stm32f10x_md.o","d:\\OneDrive\\桌面\\stm32\\9-1 串口发送\\Start\\system_stm32f10x.c":"d:\\OneDrive\\桌面\\stm32\\9-1 串口发送\\build\\Target 1\\.obj\\Start\\system_stm32f10x.o","d:\\OneDrive\\桌面\\stm32\\9-1 串口发送\\System\\delay.c":"d:\\OneDrive\\桌面\\stm32\\9-1 串口发送\\build\\Target 1\\.obj\\System\\delay.o","d:\\OneDrive\\桌面\\stm32\\9-1 串口发送\\System\\sys.c":"d:\\OneDrive\\桌面\\stm32\\9-1 串口发送\\build\\Target 1\\.obj\\System\\sys.o","d:\\OneDrive\\桌面\\stm32\\9-1 串口发送\\User\\main.c":"d:\\OneDrive\\桌面\\stm32\\9-1 串口发送\\build\\Target 1\\.obj\\User\\main.o","d:\\OneDrive\\桌面\\stm32\\9-1 串口发送\\User\\stm32f10x_it.c":"d:\\OneDrive\\桌面\\stm32\\9-1 串口发送\\build\\Target 1\\.obj\\User\\stm32f10x_it.o"}